algomojo_webhook_signal/__init__.py
algomojo_webhook_signal/signal.py
algomojo_webhook_signal-0.1.0.dist-info/licenses/LICENSE
algomojo_webhook_signal-0.1.0.dist-info/METADATA
algomojo_webhook_signal-0.1.0.dist-info/WHEEL
algomojo_webhook_signal-0.1.0.dist-info/top_level.txt
algomojo_webhook_signal-0.1.0.dist-info/RECORD
